	<PipingComponent ID="X8072" ComponentName="AngleBallValve_X8072" ComponentClass="AngleBallValve">
		<GenericAttributes Number="1" Set="DexpiAttributes">
			<GenericAttribute Name="SymbolRegistrationNumberAssignmentClass"
				Value="ISO10628-X8072"
				AttributeURI="http://sandbox.dexpi.org/rdl/SymbolRegistrationNumberAssigmentClass" />
		</GenericAttributes>
		<Extent>
			<Min X="-5" Y="-5" Z="0" />
			<Max X="2.5" Y="2.5" Z="0" />
		</Extent>
		<Position>
			<Location X="0" Y="0" Z="0" />
			<Axis X="0" Y="0" Z="1" />
			<Reference X="1" Y="0" Z="0" />
		</Position>
		<Circle Radius="2.5">
			<Presentation Layer="0" Color="0" LineType="Solid" LineWeight="0.25" R="0" G="0" B="0" />
			<Extent>
				<Min X="-2.5" Y="-2.5" />
				<Max X="2.5" Y="2.5" />
			</Extent>
			<Position>
				<Location X="0" Y="0" />
				<Axis X="0" Y="0" Z="1" />
				<Reference X="1" Y="0" Z="0" />
			</Position>
		</Circle>		
		<PolyLine NumPoints="4">
			<Presentation Layer="0" Color="0" LineType="Solid" LineWeight="0.25" R="0" G="0" B="0" />
			<Extent>
				<Min X="-5" Y="-2.5" />
				<Max X="-2.236" Y="2.5" />
			</Extent>
			<Coordinate X="-2.236" Y="-1.118" />	
			<Coordinate X="-5" Y="-2.5" />
			<Coordinate X="-5" Y="2.5" />
			<Coordinate X="-2.236" Y="1.118" />
		</PolyLine>
		<PolyLine NumPoints="4">
			<Presentation Layer="0" Color="0" LineType="Solid" LineWeight="0.25" R="0" G="0" B="0" />
			<Extent>
				<Min X="-2.5" Y="-5" />
				<Max X="2.5" Y="-2.236" />
			</Extent>
			<Coordinate X="-1.118" Y="-2.236" />	
			<Coordinate X="-2.5" Y="-5" />
			<Coordinate X="2.5" Y="-5" />
			<Coordinate X="1.118" Y="-2.236" />
		</PolyLine>
		<!-- Nodes suggested by DIN ISO 10628 -->
		<ConnectionPoints NumPoints="3" FlowIn="1" FlowOut="2">
			<!-- Node 0 : Position -->
			<Node>
				<Position>
					<Location X="0" Y="0" Z="0" />
					<Axis X="0" Y="0" Z="1" />
					<Reference X="1" Y="0" Z="0" />
				</Position>
			</Node>
			<!-- Node 1: FlowIn -->
			<Node>
				<Position>
					<Location X="-5" Y="0" Z="0" />
					<Axis X="0" Y="0" Z="1" />
					<Reference X="1" Y="0" Z="0" />
				</Position>
			</Node>
			<!-- Node 2: FlowOut -->
			<Node>
				<Position>
					<Location X="0" Y="-5" Z="0" />
					<Axis X="0" Y="0" Z="1" />
					<Reference X="1" Y="0" Z="0" />
				</Position>
			</Node>
		</ConnectionPoints>	
	</PipingComponent>